gherkin_to_markdown/__init__.py
gherkin_to_markdown/constants.py
gherkin_to_markdown/gherkin_parser.py
gherkin_to_markdown/expressions/__init__.py
gherkin_to_markdown/expressions/background_expression.py
gherkin_to_markdown/expressions/code_block_expression.py
gherkin_to_markdown/expressions/empty_expression.py
gherkin_to_markdown/expressions/example_expression.py
gherkin_to_markdown/expressions/expression.py
gherkin_to_markdown/expressions/first_header_expression.py
gherkin_to_markdown/expressions/indented_text_expression.py
gherkin_to_markdown/expressions/second_header_expression.py
gherkin_to_markdown/expressions/step_expression.py
gherkin_to_markdown/expressions/table_line_expression.py
gherkin_to_markdown/expressions/table_title_expression.py
test/__init__.py
test/test_gherkin_parser.py
gherkin_to_markdown-0.0.3.dist-info/LICENSE
gherkin_to_markdown-0.0.3.dist-info/METADATA
gherkin_to_markdown-0.0.3.dist-info/WHEEL
gherkin_to_markdown-0.0.3.dist-info/top_level.txt
gherkin_to_markdown-0.0.3.dist-info/RECORD
